{
  "code": "N8b8J",
  "brokerdata": "",
  "name": "Clemmie Coughtrey",
  "add": {
    "street": "1819 Stoughton Hill",
    "city": "Detroit",
    "state": "MI",
    "zip": "48275",
    "country": "US"
  },
  "email": [
    "ccoughtrey0@altervista.org"
  ]
}
{
  "code": "IFO6P",
  "brokerdata": "",
  "name": "Papagena Playfair",
  "add": {
    "street": "20810 Pleasure Hill",
    "city": "Fort Wayne",
    "state": "IN",
    "zip": "46825",
    "country": "US"
  },
  "email": [
    "pplayfair1@uiuc.edu"
  ]
}
{
  "code": "5FAeK",
  "brokerdata": "J",
  "name": "Chiquita Cridlin",
  "add": {
    "street": "07057 Independence Center",
    "city": "Louisville",
    "state": "KY",
    "zip": "40210",
    "country": "US"
  },
  "email": [
    "ccridlin2@howstuffworks.com"
  ]
}
{
  "code": "INWFH",
  "brokerdata": "",
  "name": "Klement Iglesias",
  "add": {
    "street": "3605 Blackbird Plaza",
    "city": "Danbury",
    "state": "CT",
    "zip": "06816",
    "country": "US"
  },
  "email": [
    "kiglesias3@php.net"
  ]
}
{
  "code": "8YR2I",
  "brokerdata": "E",
  "name": "Ketty Kydd",
  "add": {
    "street": "63 Huxley Center",
    "city": "Camden",
    "state": "NJ",
    "zip": "08104",
    "country": "US"
  },
  "email": [
    "kkydd4@redcross.org"
  ]
}
{
  "code": "XAJBb",
  "brokerdata": "",
  "name": "Thom Speek",
  "add": {
    "street": "826 Kropf Terrace",
    "city": "Riverside",
    "state": "CA",
    "zip": "92519",
    "country": "US"
  },
  "email": [
    "tspeek5@squidoo.com"
  ]
}
{
  "code": "YKu85",
  "brokerdata": "",
  "name": "Dara Kemetz",
  "add": {
    "street": "553 School Place",
    "city": "El Paso",
    "state": "TX",
    "zip": "88584",
    "country": "US"
  },
  "email": [
    "dkemetz6@wsj.com"
  ]
}
{
  "code": "AkbX8",
  "brokerdata": "",
  "name": "Guenevere Cradock",
  "add": {
    "street": "56 Erie Pass",
    "city": "Los Angeles",
    "state": "CA",
    "zip": "90094",
    "country": "US"
  },
  "email": [
    "gcradock7@globo.com"
  ]
}
{
  "code": "90GAV",
  "brokerdata": "",
  "name": "Joyce Lennon",
  "add": {
    "street": "76 Veith Hill",
    "city": "Youngstown",
    "state": "OH",
    "zip": "44555",
    "country": "US"
  },
  "email": [
    "jlennon8@xrea.com"
  ]
}
{
  "code": "CF8BK",
  "brokerdata": "",
  "name": "Kev McClaughlin",
  "add": {
    "street": "640 Dwight Road",
    "city": "Sacramento",
    "state": "CA",
    "zip": " 94286",
    "country": "US"
  },
  "email": [
    "kmcclaughlin9@engadget.com"
  ]
}
